requests_flask_adapter/__init__.py
requests_flask_adapter/adapter.py
requests_flask_adapter/helpers.py
requests_flask_adapter-0.1.0.dist-info/AUTHORS
requests_flask_adapter-0.1.0.dist-info/LICENSE
requests_flask_adapter-0.1.0.dist-info/METADATA
requests_flask_adapter-0.1.0.dist-info/WHEEL
requests_flask_adapter-0.1.0.dist-info/pbr.json
requests_flask_adapter-0.1.0.dist-info/top_level.txt
requests_flask_adapter-0.1.0.dist-info/RECORD
