Metadata-Version: 2.1
Name: requests-flask-adapter
Version: 0.1.0
Summary: Adapter for requests session to access flask apps
Home-page: https://github.com/maarten-dp/requests-flask-adapter
Author: See AUTHORS
Author-email: maarten@adimian.com
License: MIT/Expat
Platform: UNKNOWN
Classifier: Development Status :: 4 - Beta
Classifier: Operating System :: MacOS :: MacOS X
Classifier: Operating System :: Microsoft :: Windows
Classifier: Operating System :: POSIX
Classifier: License :: OSI Approved :: MIT License
Classifier: Programming Language :: Python
Classifier: Programming Language :: Python :: 3.5
Classifier: Programming Language :: Python :: 3.6
Requires-Dist: flask
Requires-Dist: requests
